proceed/__about__.py
proceed/__init__.py
proceed/aggregator.py
proceed/cli.py
proceed/config_options.py
proceed/docker_runner.py
proceed/file_matching.py
proceed/model.py
proceed/run_recorder.py
proceed/yaml_data.py
proceed-0.0.11.dist-info/METADATA
proceed-0.0.11.dist-info/WHEEL
proceed-0.0.11.dist-info/entry_points.txt
proceed-0.0.11.dist-info/licenses/LICENSE
proceed-0.0.11.dist-info/RECORD
