Metadata-Version: 2.4
Name: proceed
Version: 0.0.11
Summary: Execute pipelines based on files and containers.
Project-URL: Homepage, https://github.com/benjamin-heasly/proceed
Project-URL: Bug Tracker, https://github.com/benjamin-heasly/proceed/issues
Author-email: Ben Heasly <benjamin.heasly@gmail.com>
License-File: LICENSE
Classifier: License :: OSI Approved :: The Unlicense (Unlicense)
Classifier: Operating System :: OS Independent
Classifier: Programming Language :: Python :: 3
Requires-Python: >=3.11
Requires-Dist: docker
Requires-Dist: pandas
Requires-Dist: pyyaml
